gtoolkit_bridge/__init__.py
gtoolkit_bridge/__main__.py
gtoolkit_bridge/__version__.py
gtoolkit_bridge/PythonBridge/__init__.py
gtoolkit_bridge/PythonBridge/__main__.py
gtoolkit_bridge/PythonBridge/bridge_globals.py
gtoolkit_bridge/PythonBridge/bridge_hooks.py
gtoolkit_bridge/PythonBridge/bridge_utils.py
gtoolkit_bridge/PythonBridge/flask_platform.py
gtoolkit_bridge/PythonBridge/json_encoder.py
gtoolkit_bridge/PythonBridge/msgpack_serializer.py
gtoolkit_bridge/PythonBridge/msgpack_socket_platform.py
gtoolkit_bridge/PythonBridge/object_registry.py
gtoolkit_bridge/PythonBridge/python_bridge.py
gtoolkit_bridge/PythonBridge/stoppable_thread.py
gtoolkit_bridge/PythonBridge/telemetry.py
gtoolkit_bridge/PythonBridge/tfactorial.py
gtoolkit_bridge/PythonBridge/tmp.py
gtoolkit_bridge/gtoolkit/gt.py
gtoolkit_bridge/gtoolkit/gt_test_support.py
gtoolkit_bridge/gtoolkit/phlow/column.py
gtoolkit_bridge/gtoolkit/phlow/data_source.py
gtoolkit_bridge/gtoolkit/phlow/text.py
gtoolkit_bridge/gtoolkit/phlow/view.py
gtoolkit_bridge/gtoolkit/phlow/view_builder.py
gtoolkit_bridge/gtoolkit/phlow/view_columnedlist.py
gtoolkit_bridge/gtoolkit/phlow/view_columnedtree.py
gtoolkit_bridge/gtoolkit/phlow/view_empty.py
gtoolkit_bridge/gtoolkit/phlow/view_error.py
gtoolkit_bridge/gtoolkit/phlow/view_forward.py
gtoolkit_bridge/gtoolkit/phlow/view_list.py
gtoolkit_bridge/gtoolkit/phlow/view_texteditor.py
gtoolkit_bridge-0.3.4.dist-info/LICENSE
gtoolkit_bridge-0.3.4.dist-info/WHEEL
gtoolkit_bridge-0.3.4.dist-info/METADATA
gtoolkit_bridge-0.3.4.dist-info/RECORD
