Metadata-Version: 2.1
Name: gtoolkit_bridge
Version: 0.3.4
Summary: Glamorous Toolkit Python Bridge
Author-email: feenk team <gt@feenk.com>
Requires-Python: >=3.8,<4
Classifier: License :: OSI Approved :: MIT License
Requires-Dist: requests
Requires-Dist: Flask
Requires-Dist: msgpack
Project-URL: Home, https://gtoolkit.com
